aiohttp_google_auth_backend/__init__.py
aiohttp_google_auth_backend-0.5.1.dist-info/COPYING
aiohttp_google_auth_backend-0.5.1.dist-info/METADATA
aiohttp_google_auth_backend-0.5.1.dist-info/WHEEL
aiohttp_google_auth_backend-0.5.1.dist-info/top_level.txt
aiohttp_google_auth_backend-0.5.1.dist-info/RECORD
