Metadata-Version: 2.1
Name: aiohttp-google-auth-backend
Version: 0.5.1
Summary: Asyncio wrapper for verify_token method in google-auth library for backend usage
Home-page: https://github.com/ketanbshah/aiohttp_google_auth_backend
Author: Ketan B Shah, JyotiStar Inc
Author-email: shahketanb@gmail.com
License: GPL-3.0-only
Platform: UNKNOWN
Requires-Python: >=3.8
